{
	"name": "src_copy01",
	"properties": {
		"linkedServiceName": {
			"referenceName": "AzureDataLakeStorage1",
			"type": "LinkedServiceReference"
		},
		"annotations": [],
		"type": "DelimitedText",
		"typeProperties": {
			"location": {
				"type": "AzureBlobFSLocation",
				"fileName": "Resume_Points.txt",
				"fileSystem": "targetee"
			},
			"columnDelimiter": ",",
			"escapeChar": "\\",
			"firstRowAsHeader": true,
			"quoteChar": "\""
		},
		"schema": [
			{
				"name": "####[2026-02-24T05:08:14.841+00:00] [INFO] dummy file is deleted",
				"type": "String"
			}
		]
	},
	"type": "Microsoft.DataFactory/factories/datasets"
}